gitlab2prov/__init__.py
gitlab2prov/bootstrap.py
gitlab2prov/log.py
gitlab2prov/root.py
gitlab2prov/adapters/__init__.py
gitlab2prov/adapters/repository.py
gitlab2prov/adapters/fetch/__init__.py
gitlab2prov/adapters/fetch/git.py
gitlab2prov/adapters/fetch/gitlab.py
gitlab2prov/adapters/fetch/utils.py
gitlab2prov/adapters/fetch/annotations/__init__.py
gitlab2prov/adapters/fetch/annotations/classifiers.py
gitlab2prov/adapters/fetch/annotations/parse.py
gitlab2prov/config/__init__.py
gitlab2prov/config/parser.py
gitlab2prov/domain/__init__.py
gitlab2prov/domain/commands.py
gitlab2prov/domain/constants.py
gitlab2prov/domain/objects.py
gitlab2prov/entrypoints/__init__.py
gitlab2prov/entrypoints/cli.py
gitlab2prov/prov/__init__.py
gitlab2prov/prov/model.py
gitlab2prov/prov/operations.py
gitlab2prov/service_layer/__init__.py
gitlab2prov/service_layer/handlers.py
gitlab2prov/service_layer/messagebus.py
gitlab2prov/service_layer/unit_of_work.py
gitlab2prov-2.1.0.dist-info/LICENSE
gitlab2prov-2.1.0.dist-info/METADATA
gitlab2prov-2.1.0.dist-info/WHEEL
gitlab2prov-2.1.0.dist-info/entry_points.txt
gitlab2prov-2.1.0.dist-info/top_level.txt
gitlab2prov-2.1.0.dist-info/RECORD
