Metadata-Version: 2.1
Name: gitlab2prov
Version: 2.1.0
Summary: Extract provenance information (W3C PROV) from GitLab projects.
Author-email: Claas de Boer <claas.deboer@dlr.de>
Maintainer-email: Andreas Schreiber <andreas.schreiber@dlr.de>
License: MIT License
Project-URL: Twitter, https://twitter.com/dlr_software
Project-URL: Source Code, https://github.com/dlr-sc/gitlab2prov
Project-URL: Issue Tracker, https://github.com/dlr-sc/gitlab2prov/issues
Keywords: prov,gitlab,git,provenance,prov generation,software analytics,w3c prov
Classifier: Development Status :: 5 - Production/Stable
Classifier: Environment :: Console
Classifier: Intended Audience :: Science/Research
Classifier: License :: OSI Approved :: MIT License
Classifier: Programming Language :: Python
Classifier: Programming Language :: Python :: 3 :: Only
Classifier: Topic :: Scientific/Engineering
Classifier: Topic :: Scientific/Engineering :: Information Analysis
Classifier: Topic :: Software Development :: Version Control :: Git
Requires-Python: >=3.10
License-File: LICENSE
Requires-Dist: prov (>=2.0.0)
Requires-Dist: git-python
Requires-Dist: python-gitlab
Requires-Dist: jsonschema
Requires-Dist: ruamel.yaml
Requires-Dist: pydot (>=1.2.0)
Requires-Dist: click
Provides-Extra: dev
Requires-Dist: pytest ; extra == 'dev'
Requires-Dist: pytest-mock ; extra == 'dev'
Requires-Dist: black ; extra == 'dev'
Requires-Dist: isort ; extra == 'dev'
Requires-Dist: bump2version ; extra == 'dev'
